bw_requests/__init__.py
bw_requests/bw_requests.py
bw_requests/cRequests.py
bw_requests/useragent.py
bw_requests-0.0.2.dist-info/LICENSE
bw_requests-0.0.2.dist-info/METADATA
bw_requests-0.0.2.dist-info/WHEEL
bw_requests-0.0.2.dist-info/top_level.txt
bw_requests-0.0.2.dist-info/RECORD
