Metadata-Version: 2.1
Name: bw-requests
Version: 0.0.2
Summary: HTTP Requests Module
Author-email: Rosario Sensale <pcassistenzatecnica@gmail.com>
Project-URL: Homepage, https://pypi.org/user/AloneInTheDark/
Project-URL: Bug Tracker, https://pypi.org/user/AloneInTheDark/
Classifier: Programming Language :: Python :: 3
Classifier: License :: OSI Approved :: MIT License
Classifier: Operating System :: OS Independent
Requires-Python: >=3.7
License-File: LICENSE
Requires-Dist: requests
